calculadora/__init__.py
calculadora/calculadora.py
calculadora_test-0.0.1.dist-info/METADATA
calculadora_test-0.0.1.dist-info/WHEEL
calculadora_test-0.0.1.dist-info/top_level.txt
calculadora_test-0.0.1.dist-info/RECORD
