Metadata-Version: 2.4
Name: calculadora_test
Version: 0.0.1
Summary: Um pacote simples de calculadora em Python
Home-page: 
Author: Pablo
Requires-Python: >=3.5
Dynamic: author
Dynamic: description
Dynamic: description-content-type
Dynamic: requires-python
Dynamic: summary
